nibelis_dl.py
nibelis_dl-1.0.0.dist-info/DESCRIPTION.rst
nibelis_dl-1.0.0.dist-info/METADATA
nibelis_dl-1.0.0.dist-info/RECORD
nibelis_dl-1.0.0.dist-info/WHEEL
nibelis_dl-1.0.0.dist-info/entry_points.txt
nibelis_dl-1.0.0.dist-info/metadata.json
nibelis_dl-1.0.0.dist-info/top_level.txt
